[
  {
    "title": "Circuits",
    "text": "In this section you can see <strong>all</strong> the characteristic F1 circuits.",
    "img_url": "https://media.formula1.com/image/upload/content/dam/fom-website/2018-redesign-assets/Circuit%20maps%2016x9/USA_Circuit.png",
    "link": "#"
  },
  {
    "title": "FIA Regulations Formula One World Championship",
    "text": "Have fun in reading these <strong>short</strong> docs <strong>:P</strong>",
    "img_url": "https://i.ytimg.com/vi/jKZKCl_GEgY/maxresdefault.jpg",
    "link": "https://www.fia.com/regulation/category/110"
  },
  {
    "title": "Drivers",
    "text": "Discover the secrets of your favorite Drivers <strong>:)</strong>",
    "img_url": "https://www.sportinglad.com/wp-content/uploads/2023/08/ezgif.com-gif-maker.webp",
    "link": "#"
  },
  {
    "title": "Teams",
    "text": "Discover the <strong>history</strong> of each Team",
    "img_url": "https://f1ntastic.com/wp-content/uploads/2022/03/2022-F1-Teams-Cover.jpg",
    "link": "#"
  },
  {
    "title": "Statistics",
    "text": "<strong>Data</strong> lover? This section is for you!",
    "img_url": "https://hoteldelaville.com/wp-content/uploads/2021/06/gran-premio-di-monza-informazioni-1000x634.jpg",
    "link": "#"
  },
  {
    "title": "Store",
    "text": "Buy <strong>official</strong> merchandise",
    "img_url": "https://cdn-5.motorsport.com/images/amp/0qXjNlQ6/s6/charles-leclerc-ferrari-carlos.jpg",
    "link": "#"
  }
]